strainmap/__init__.py
strainmap/__main__.py
strainmap/controller.py
strainmap/coordinates.py
strainmap/entrypoints.py
strainmap/exceptions.py
strainmap/gui/__init__.py
strainmap/gui/base_window_and_task.py
strainmap/gui/data_view.py
strainmap/gui/figure_actions.py
strainmap/gui/figure_actions_manager.py
strainmap/gui/icons/CREDITS.md
strainmap/gui/icons/atlas.gif
strainmap/gui/icons/molecules.gif
strainmap/gui/icons/save.gif
strainmap/gui/icons/speed.gif
strainmap/gui/icons/strain.gif
strainmap/gui/markers_figure.py
strainmap/gui/segmentation_view.py
strainmap/gui/velocities_view.py
strainmap/models/__init__.py
strainmap/models/ai_segmenter.py
strainmap/models/contour_mask.py
strainmap/models/filters.py
strainmap/models/legacy.py
strainmap/models/propagators.py
strainmap/models/readers.py
strainmap/models/segmentation.py
strainmap/models/snakes_segmenter.py
strainmap/models/strainmap_data_model.py
strainmap/models/transformations.py
strainmap/models/velocities.py
strainmap/models/writers.py
strainmap/tools.py
strainmap-1.2.9.dist-info/LICENSE
strainmap-1.2.9.dist-info/METADATA
strainmap-1.2.9.dist-info/WHEEL
strainmap-1.2.9.dist-info/entry_points.txt
strainmap-1.2.9.dist-info/RECORD
