Metadata-Version: 2.1
Name: strainmap
Version: 1.2.9
Summary: 
Home-page: https://github.com/imperialcollegelondon/strainmap
License: GPL-3.0-or-later
Author: RSE Team, Research Computing Service, Imperial College London
Author-email: ict-rse-team@imperial.ac.uk
Requires-Python: >=3.8,<3.11
Classifier: Development Status :: 5 - Production/Stable
Classifier: Environment :: MacOS X
Classifier: Environment :: Win32 (MS Windows)
Classifier: Environment :: X11 Applications
Classifier: Intended Audience :: End Users/Desktop
Classifier: Intended Audience :: Science/Research
Classifier: License :: OSI Approved :: GNU General Public License v3 or later (GPLv3+)
Classifier: Programming Language :: Python :: 3
Classifier: Programming Language :: Python :: 3.8
Classifier: Programming Language :: Python :: 3.9
Classifier: Programming Language :: Python :: 3.10
Requires-Dist: PyPubSub (>=4.0.3,<5.0.0)
Requires-Dist: h5py (<=3.6)
Requires-Dist: keras (<=2.8)
Requires-Dist: matplotlib (<3.6.0)
Requires-Dist: natsort (>=8.2.0,<9.0.0)
Requires-Dist: netCDF4 (>=1.6.1,<2.0.0)
Requires-Dist: nibabel (>=4.0.2,<5.0.0)
Requires-Dist: opencv-python (>=4.6.0,<5.0.0)
Requires-Dist: openpyxl (>=3.0.10,<4.0.0)
Requires-Dist: protobuf (<=3.20)
Requires-Dist: pydicom (>=2.3.0,<3.0.0)
Requires-Dist: python-decouple (>=3.6,<4.0)
Requires-Dist: scipy (>=1.9.1,<2.0.0)
Requires-Dist: tensorflow (<=2.8)
Requires-Dist: tensorlayer (<=2.2)
Requires-Dist: tqdm (>=4.64.1,<5.0.0)
Requires-Dist: xarray (>=2022.6.0,<2023.0.0)
Project-URL: Repository, https://github.com/ImperialCollegeLondon/strainmap
